{
  "last_updated": "2025-04-22T19:18:43.628165Z",
  "themes": {
    "Consolized.theme": {
      "preview_path": "Catalog/Themes/previews/Consolized.theme.png",
      "manifest_path": "Catalog/Themes/manifests/Consolized.theme.json",
      "author": "Gamnrd",
      "description": "Consolized.theme",
      "URL": "https://github.com/Leviathanium/NextUI-Themes/raw/main/Uploads/Themes/Consolized.theme.zip"
    },
    "Default.theme": {
      "preview_path": "Catalog/Themes/previews/Default.theme.png",
      "manifest_path": "Catalog/Themes/manifests/Default.theme.json",
      "author": "NextUI",
      "description": "Default.theme",
      "URL": "https://github.com/Leviathanium/NextUI-Themes/raw/main/Uploads/Themes/Default.theme.zip"
    }
  },
  "components": {
    "accents": {},
    "leds": {},
    "icons": {},
    "fonts": {},
    "wallpapers": {},
    "overlays": {}
  }
}